dalux_client/__init__.py
dalux_client/api/__init__.py
dalux_client/api/companies_api.py
dalux_client/api/company_catalog_api.py
dalux_client/api/file_areas_api.py
dalux_client/api/file_revisions_api.py
dalux_client/api/file_upload_api.py
dalux_client/api/files_api.py
dalux_client/api/folders_api.py
dalux_client/api/forms_api.py
dalux_client/api/inspection_plans_api.py
dalux_client/api/project_templates_api.py
dalux_client/api/projects_api.py
dalux_client/api/tasks_api.py
dalux_client/api/test_plans_api.py
dalux_client/api/users_api.py
dalux_client/api/version_sets_api.py
dalux_client/api/work_packages_api.py
dalux_client/api_client.py
dalux_client/configuration.py
dalux_client/models/__init__.py
dalux_client/models/api_task_get.py
dalux_client/models/basic_field_mapping.py
dalux_client/models/bim_object.py
dalux_client/models/building_reference.py
dalux_client/models/catalog_company_metadata.py
dalux_client/models/catalog_company_metadata_field_value.py
dalux_client/models/catalogue_company.py
dalux_client/models/coordinate3_d.py
dalux_client/models/date_change.py
dalux_client/models/date_mapping_value.py
dalux_client/models/date_time_mapping_value.py
dalux_client/models/drawing_reference.py
dalux_client/models/error_field.py
dalux_client/models/error_model.py
dalux_client/models/file.py
dalux_client/models/file_area.py
dalux_client/models/file_date_property.py
dalux_client/models/file_integer_property.py
dalux_client/models/file_property_field.py
dalux_client/models/file_property_mapping.py
dalux_client/models/file_reference_property.py
dalux_client/models/file_text_property.py
dalux_client/models/folder.py
dalux_client/models/form.py
dalux_client/models/form_attachment.py
dalux_client/models/form_attachment_relation.py
dalux_client/models/form_attachment_relation_user_defined_field.py
dalux_client/models/form_user_defined_fields.py
dalux_client/models/form_user_field_relation.py
dalux_client/models/gps.py
dalux_client/models/inline_response200.py
dalux_client-0.1.3.dist-info/WHEEL
dalux_client-0.1.3.dist-info/entry_points.txt
dalux_client-0.1.3.dist-info/METADATA
dalux_client-0.1.3.dist-info/RECORD
