Metadata-Version: 2.3
Name: dalux-client
Version: 0.1.3
Summary: Add your description here
Author: Eivind Teig
Author-email: Eivind Teig <eivind.teig@gmail.com>
Requires-Dist: certifi>=14.5.14
Requires-Dist: python-dateutil>=2.5.3
Requires-Dist: setuptools>=21.0.0
Requires-Dist: six>=1.10
Requires-Dist: urllib3>=1.15.1
Requires-Python: >=3.14.0
